multiviewica/__init__.py
multiviewica/_groupica.py
multiviewica/_multiviewica.py
multiviewica/_permica.py
multiviewica/reduce_data.py
multiviewica-0.0.1.dist-info/LICENSE
multiviewica-0.0.1.dist-info/METADATA
multiviewica-0.0.1.dist-info/WHEEL
multiviewica-0.0.1.dist-info/top_level.txt
multiviewica-0.0.1.dist-info/RECORD
