Metadata-Version: 2.1
Name: multiviewica
Version: 0.0.1
Summary: Multi-view ICA
Home-page: UNKNOWN
License: UNKNOWN
Platform: UNKNOWN
Requires-Python: >=3
Requires-Dist: numpy (>=1.12)
Requires-Dist: scikit-learn (>=0.23)
Requires-Dist: python-picard
Requires-Dist: fastsrm
Requires-Dist: scipy (>=0.18.0)
Requires-Dist: matplotlib (>=2.0.0)
